setup.py
molp/__init__.py
molp/admin.py
molp/models.py
molp/tests.py
molp/views.py
molp.egg-info/PKG-INFO
molp.egg-info/SOURCES.txt
molp.egg-info/dependency_links.txt
molp.egg-info/top_level.txt