Metadata-Version: 1.0
Name: molp
Version: 0.5.2
Summary: online parameters for app mobile
Home-page: https://github.com/jeffkit/molp
Author: jeff kit
Author-email: bbmyth@gmail.com
License: UNKNOWN
Platform: UNKNOWN
